loggutils.py
loggutils-0.1.0.dist-info/METADATA
loggutils-0.1.0.dist-info/WHEEL
loggutils-0.1.0.dist-info/top_level.txt
loggutils-0.1.0.dist-info/RECORD
