Metadata-Version: 2.4
Name: loggutils
Version: 0.1.0
Summary: Утилиты для логгирования
Author-email: Michael <stroytell049@gmail.com>
License: MIT
Requires-Python: >=3.7
